{"analysis": {"adg": 0.000697510447692121,
              "drawdown_worst": 0.15312455285740986,
              "equity_balance_diff_max": 0.14339572657007657,
              "equity_balance_diff_mean": 0.00885899801782795,
              "loss_profit_ratio": 0.5672414988562828,
              "mdg": 0.00028332059761246683,
              "n_iters": 9493,
              "sharpe_ratio": 0.11471281912569702,
              "w_0": -0.00028332059761246683,
              "w_1": -0.11471281912569702},
 "backtest": {"base_dir": "backtests",
              "end_date": "now",
              "exchange": "binance",
              "start_date": "2021-05-01",
              "starting_balance": 100000,
              "symbols": ["LINKUSDT"]},
 "bot": {"long": {"close_grid_markup_range": 0.052036016672767665,
                  "close_grid_min_markup": 0.03239760070567887,
                  "close_grid_qty_pct": 0.8099961918211325,
                  "close_trailing_grid_ratio": -0.3655617020210955,
                  "close_trailing_qty_pct": 0.6961630572696722,
                  "close_trailing_retracement_pct": 0.09205823814814497,
                  "close_trailing_threshold_pct": -0.02494698927302324,
                  "ema_span_0": 370.0874296413525,
                  "ema_span_1": 941.6580570532626,
                  "entry_grid_double_down_factor": 0.11037539102541816,
                  "entry_grid_spacing_pct": 0.08783436383284113,
                  "entry_grid_spacing_weight": 9.163411898548217,
                  "entry_initial_ema_dist": -0.01864693008389455,
                  "entry_initial_qty_pct": 0.006214825213786766,
                  "entry_trailing_grid_ratio": -0.5737534254498178,
                  "entry_trailing_retracement_pct": 0.08045332674545816,
                  "entry_trailing_threshold_pct": -0.06402913422602295,
                  "filter_relative_volume_clip_pct": 0.42507625520027814,
                  "filter_rolling_window": 1288.3621976328773,
                  "n_positions": 1,
                  "total_wallet_exposure_limit": 2.5,
                  "unstuck_close_pct": 0.02233721482331123,
                  "unstuck_ema_dist": -0.09716910245512947,
                  "unstuck_loss_allowance_pct": 0.04005401155698127,
                  "unstuck_threshold": 0.48641491793690106},
         "short": {"close_grid_markup_range": 0.013417801546097192,
                   "close_grid_min_markup": 0.016931090056723788,
                   "close_grid_qty_pct": 0.35394149244246836,
                   "close_trailing_grid_ratio": -0.12836074806643433,
                   "close_trailing_qty_pct": 0.4284654015741613,
                   "close_trailing_retracement_pct": 0.028216884060315087,
                   "close_trailing_threshold_pct": -0.05367984752028213,
                   "ema_span_0": 233.6520938454152,
                   "ema_span_1": 542.5155583091042,
                   "entry_grid_double_down_factor": 1.2546783243412392,
                   "entry_grid_spacing_pct": 0.04320710852457703,
                   "entry_grid_spacing_weight": 8.71765052950239,
                   "entry_initial_ema_dist": -0.07651759841733673,
                   "entry_initial_qty_pct": 0.0444809856006233,
                   "entry_trailing_grid_ratio": -0.944203671482996,
                   "entry_trailing_retracement_pct": 0.005785208574637261,
                   "entry_trailing_threshold_pct": 0.033561636928109095,
                   "filter_relative_volume_clip_pct": 0.7684735476186013,
                   "filter_rolling_window": 1281.3877975579057,
                   "n_positions": 1,
                   "total_wallet_exposure_limit": 1,
                   "unstuck_close_pct": 0.08868339920383189,
                   "unstuck_ema_dist": -0.09491587218497714,
                   "unstuck_loss_allowance_pct": 0.014508304558618653,
                   "unstuck_threshold": 0.8505951649775875}},
 "live": {"approved_coins": ["LINKUSDT"],
          "auto_gs": true,
          "coin_flags": {},
          "execution_delay_seconds": 2,
          "filter_by_min_effective_cost": true,
          "forced_mode_long": "",
          "forced_mode_short": "",
          "ignored_coins": [],
          "leverage": 10,
          "max_n_cancellations_per_batch": 5,
          "max_n_creations_per_batch": 3,
          "minimum_coin_age_days": 30,
          "ohlcv_rolling_window": 60,
          "pnls_max_lookback_days": 30,
          "price_distance_threshold": 0.002,
          "relative_volume_filter_clip_pct": 0.5,
          "time_in_force": "good_till_cancelled",
          "user": "hyperliquid_v7"},
 "optimize": {"bounds": {"long_close_grid_markup_range": [0, 0.06],
                         "long_close_grid_min_markup": [0.001, 0.06],
                         "long_close_grid_qty_pct": [0.05, 1],
                         "long_close_trailing_grid_ratio": [-1, 1],
                         "long_close_trailing_qty_pct": [0.05, 1],
                         "long_close_trailing_retracement_pct": [0, 0.3],
                         "long_close_trailing_threshold_pct": [-0.1, 0.1],
                         "long_ema_span_0": [200, 1440],
                         "long_ema_span_1": [200, 1440],
                         "long_entry_grid_double_down_factor": [0.1, 3],
                         "long_entry_grid_spacing_pct": [0.001, 0.12],
                         "long_entry_grid_spacing_weight": [0, 10],
                         "long_entry_initial_ema_dist": [-0.1, 0.003],
                         "long_entry_initial_qty_pct": [0.005, 0.1],
                         "long_entry_trailing_grid_ratio": [-1, 1],
                         "long_entry_trailing_retracement_pct": [0, 0.1],
                         "long_entry_trailing_threshold_pct": [-0.1, 0.1],
                         "long_filter_relative_volume_clip_pct": [0, 1],
                         "long_filter_rolling_window": [10, 1440],
                         "long_n_positions": [1, 1],
                         "long_total_wallet_exposure_limit": [2.5, 2.5],
                         "long_unstuck_close_pct": [0.001, 0.1],
                         "long_unstuck_ema_dist": [-0.1, 0.01],
                         "long_unstuck_loss_allowance_pct": [0, 0.05],
                         "long_unstuck_threshold": [0.4, 0.95],
                         "short_close_grid_markup_range": [0, 0.03],
                         "short_close_grid_min_markup": [0.001, 0.03],
                         "short_close_grid_qty_pct": [0.05, 1],
                         "short_close_trailing_grid_ratio": [-1, 1],
                         "short_close_trailing_qty_pct": [0.05, 1],
                         "short_close_trailing_retracement_pct": [0, 0.1],
                         "short_close_trailing_threshold_pct": [-0.1, 0.1],
                         "short_ema_span_0": [200, 1440],
                         "short_ema_span_1": [200, 1440],
                         "short_entry_grid_double_down_factor": [0.1, 3],
                         "short_entry_grid_spacing_pct": [0.001, 0.12],
                         "short_entry_grid_spacing_weight": [0, 10],
                         "short_entry_initial_ema_dist": [-0.1, 0.003],
                         "short_entry_initial_qty_pct": [0.005, 0.1],
                         "short_entry_trailing_grid_ratio": [-1, 1],
                         "short_entry_trailing_retracement_pct": [0, 0.1],
                         "short_entry_trailing_threshold_pct": [-0.1, 0.1],
                         "short_filter_relative_volume_clip_pct": [0, 1],
                         "short_filter_rolling_window": [10, 1440],
                         "short_n_positions": [1, 1],
                         "short_total_wallet_exposure_limit": [1, 1],
                         "short_unstuck_close_pct": [0.001, 0.1],
                         "short_unstuck_ema_dist": [-0.1, 0.01],
                         "short_unstuck_loss_allowance_pct": [0, 0.05],
                         "short_unstuck_threshold": [0.4, 0.95]},
              "crossover_probability": 0.7,
              "iters": 10000,
              "limits": {"lower_bound_drawdown_worst": 0.25,
                         "lower_bound_equity_balance_diff_mean": 0.01,
                         "lower_bound_loss_profit_ratio": 0.6},
              "mutation_probability": 0.2,
              "n_cpus": 8,
              "population_size": 500,
              "scoring": ["mdg", "sharpe_ratio"]},
 "results_filename": "optimize_results/2024-10-07T12_56_16_LINK_6bbec61b_all_results.txt"}