{
    "config_name": "recursive_grid_0days",
    "long": {
        "auto_unstuck_ema_dist": 0.005,
        "auto_unstuck_wallet_exposure_threshold": 0.05012488381543397,
        "backwards_tp": true,
        "ddown_factor": 2.0021305083144223,
        "ema_span_0": 191.2722057704201,
        "ema_span_1": 182.76091274515431,
        "enabled": true,
        "initial_eprice_ema_dist": -0.0172035776301481,
        "initial_qty_pct": 0.02149348038539894,
        "markup_range": 0.0,
        "min_markup": 0.0036096964783379356,
        "n_close_orders": 10,
        "rentry_pprice_dist": 0.028236974869111704,
        "rentry_pprice_dist_wallet_exposure_weighting": 3.677641431755543,
        "wallet_exposure_limit": 0.3
    },
    "short": {
        "auto_unstuck_ema_dist": 0,
        "auto_unstuck_wallet_exposure_threshold": 0.04075945900832553,
        "backwards_tp": true,
        "ddown_factor": 1.1404549840244773,
        "ema_span_0": 1355.5495231062775,
        "ema_span_1": 846.0439894134338,
        "enabled": true,
        "initial_eprice_ema_dist": -0.0046426080373854,
        "initial_qty_pct": 0.019032016019779902,
        "markup_range": 0.013227242328960614,
        "min_markup": 0.006446785827338818,
        "n_close_orders": 11,
        "rentry_pprice_dist": 0.030160044798955437,
        "rentry_pprice_dist_wallet_exposure_weighting": 3.862030942834296,
        "wallet_exposure_limit": 1
    }
}